mascope_jupyter_widgets/click_event_handler/click_event_handler.py
mascope_jupyter_widgets/click_event_handler/helpers.py
mascope_jupyter_widgets/click_event_handler/callbacks.py
mascope_jupyter_widgets/click_event_handler/__init__.py
mascope_jupyter_widgets/mass_defect/extension.py
mascope_jupyter_widgets/mass_defect/widgets.py
mascope_jupyter_widgets/mass_defect/README.md
mascope_jupyter_widgets/mass_defect/plots.py
mascope_jupyter_widgets/mass_defect/schemas.py
mascope_jupyter_widgets/mass_defect/__init__.py
mascope_jupyter_widgets/README.md
mascope_jupyter_widgets/binning/extension.py
mascope_jupyter_widgets/binning/widgets.py
mascope_jupyter_widgets/binning/plots.py
mascope_jupyter_widgets/binning/plots_utils.py
mascope_jupyter_widgets/binning/schemas.py
mascope_jupyter_widgets/binning/__init__.py
mascope_jupyter_widgets/alignment/extension.py
mascope_jupyter_widgets/alignment/widgets.py
mascope_jupyter_widgets/alignment/__init__.py
mascope_jupyter_widgets/widgets_config.py
mascope_jupyter_widgets/plot_tools.py
mascope_jupyter_widgets/logging_config.py
mascope_jupyter_widgets/timeseries/extension.py
mascope_jupyter_widgets/timeseries/widgets.py
mascope_jupyter_widgets/timeseries/README.md
mascope_jupyter_widgets/timeseries/plots.py
mascope_jupyter_widgets/timeseries/schemas.py
mascope_jupyter_widgets/timeseries/__init__.py
mascope_jupyter_widgets/peak_visualization/extension.py
mascope_jupyter_widgets/peak_visualization/widgets.py
mascope_jupyter_widgets/peak_visualization/plots.py
mascope_jupyter_widgets/peak_visualization/__init__.py
mascope_jupyter_widgets/sample_timeseries/extension.py
mascope_jupyter_widgets/sample_timeseries/widgets.py
mascope_jupyter_widgets/sample_timeseries/plots.py
mascope_jupyter_widgets/sample_timeseries/schemas.py
mascope_jupyter_widgets/sample_timeseries/__init__.py
mascope_jupyter_widgets/mascope_data/lib/dropdown.py
mascope_jupyter_widgets/mascope_data/lib/multiselect.py
mascope_jupyter_widgets/mascope_data/lib/__init__.py
mascope_jupyter_widgets-2026.1.16.post2.dist-info/WHEEL
mascope_jupyter_widgets-2026.1.16.post2.dist-info/METADATA
mascope_jupyter_widgets-2026.1.16.post2.dist-info/RECORD
