Metadata-Version: 2.3
Name: mascope-jupyter-widgets
Version: 2026.1.16.post2
Summary: Interactive widgets to construct data analysis notebooks for Mascope
Author: Jussi Vehviläinen, Oskari Kausiala, Konstantin Tumashevich
Author-email: Jussi Vehviläinen <jussi.vehvilainen@karsa.fi>, Oskari Kausiala <oskari.kausiala@karsa.fi>, Konstantin Tumashevich <konstantin.tumashevich@karsa.fi>
License: MIT
Requires-Dist: mascope-sdk>=2025.10.14
Requires-Dist: mascope-tools>=2025.10.27
Requires-Dist: pandas>=2.2.3,<3.0.0
Requires-Dist: pandera>=0.22.1,<0.23.0
Requires-Dist: ipywidgets>=8.1.5,<9.0.0
Requires-Dist: numpy>=2.2.2,<3.0.0
Requires-Dist: tqdm>=4.67.1,<5.0.0
Requires-Dist: python-dotenv>=1.0.1,<2.0.0
Requires-Dist: colorcet>=3.1.0,<4.0.0
Requires-Dist: plotly==5.24.1
Requires-Dist: ipyaggrid>=0.5.4,<0.6.0
Requires-Dist: matplotlib>=3.10.1,<4.0.0
Requires-Dist: seaborn>=0.13.2,<0.14.0
Requires-Dist: scipy>=1.15.2,<2.0.0
Requires-Dist: pandarallel>=1.6.5,<2.0.0
Requires-Dist: loguru>=0.7.3
Requires-Dist: statsmodels>=0.14.4
Requires-Dist: isospecpy>=2.2.3
Requires-Dist: nbformat>=5.10.4
Requires-Dist: molmass>=2025.4.14
Requires-Python: >=3.12, <3.14
